awslabs/__init__.py
awslabs/amazon_sns_sqs_mcp_server/__init__.py
awslabs/amazon_sns_sqs_mcp_server/common.py
awslabs/amazon_sns_sqs_mcp_server/consts.py
awslabs/amazon_sns_sqs_mcp_server/generator.py
awslabs/amazon_sns_sqs_mcp_server/server.py
awslabs/amazon_sns_sqs_mcp_server/sns.py
awslabs/amazon_sns_sqs_mcp_server/sqs.py
awslabs_amazon_sns_sqs_mcp_server-2.0.13.dist-info/METADATA
awslabs_amazon_sns_sqs_mcp_server-2.0.13.dist-info/WHEEL
awslabs_amazon_sns_sqs_mcp_server-2.0.13.dist-info/entry_points.txt
awslabs_amazon_sns_sqs_mcp_server-2.0.13.dist-info/licenses/LICENSE
awslabs_amazon_sns_sqs_mcp_server-2.0.13.dist-info/licenses/NOTICE
awslabs_amazon_sns_sqs_mcp_server-2.0.13.dist-info/RECORD
